fretsonfire/Audio.py
fretsonfire/Camera.py
fretsonfire/Cerealizer.py
fretsonfire/Collada.py
fretsonfire/Config.py
fretsonfire/Credits.py
fretsonfire/Data.py
fretsonfire/Debug.py
fretsonfire/DialogTest.py
fretsonfire/Dialogs.py
fretsonfire/DummyAmanith.py
fretsonfire/Editor.py
fretsonfire/Engine.py
fretsonfire/Font.py
fretsonfire/FretsOnFire.py
fretsonfire/GameEngine.py
fretsonfire/GameEngineTest.py
fretsonfire/GameResultsScene.py
fretsonfire/GameTask.py
fretsonfire/Guitar.py
fretsonfire/GuitarScene.py
fretsonfire/Input.py
fretsonfire/Language.py
fretsonfire/Lobby.py
fretsonfire/Log.py
fretsonfire/MainMenu.py
fretsonfire/Menu.py
fretsonfire/MenuTest.py
fretsonfire/Mesh.py
fretsonfire/Messages.py
fretsonfire/Mod.py
fretsonfire/Network.py
fretsonfire/Object.py
fretsonfire/Player.py
fretsonfire/Resource.py
fretsonfire/Scene.py
fretsonfire/SceneFactory.py
fretsonfire/SceneTest.py
fretsonfire/Server.py
fretsonfire/Session.py
fretsonfire/Settings.py
fretsonfire/Song.py
fretsonfire/SongChoosingScene.py
fretsonfire/Stage.py
fretsonfire/Svg.py
fretsonfire/SvgColors.py
fretsonfire/SvgTest.py
fretsonfire/Task.py
fretsonfire/TestAll.py
fretsonfire/Texture.py
fretsonfire/Theme.py
fretsonfire/Timer.py
fretsonfire/Version.py
fretsonfire/Video.py
fretsonfire/VideoTest.py
fretsonfire/View.py
fretsonfire/ViewTest.py
fretsonfire/World.py
fretsonfire/__init__.py
fretsonfire/__main__.py
fretsonfire/_build.py
fretsonfire/data/2x.png
fretsonfire/data/2x.svg
fretsonfire/data/3x.png
fretsonfire/data/3x.svg
fretsonfire/data/4x.png
fretsonfire/data/4x.svg
fretsonfire/data/PyOpenGL__init__.pyc
fretsonfire/data/ball1.png
fretsonfire/data/ball1.svg
fretsonfire/data/ball2.png
fretsonfire/data/ball2.svg
fretsonfire/data/bar.png
fretsonfire/data/bar.svg
fretsonfire/data/cassette.3DS
fretsonfire/data/cassette.dae
fretsonfire/data/cassette.png
fretsonfire/data/cassette.svg
fretsonfire/data/crunch1.ogg
fretsonfire/data/crunch2.ogg
fretsonfire/data/crunch3.ogg
fretsonfire/data/cube.dae
fretsonfire-1.6.1.dist-info/licenses/LICENSE.md
fretsonfire-1.6.1.dist-info/METADATA
fretsonfire-1.6.1.dist-info/WHEEL
fretsonfire-1.6.1.dist-info/entry_points.txt
fretsonfire-1.6.1.dist-info/top_level.txt
fretsonfire-1.6.1.dist-info/RECORD
