Metadata-Version: 2.4
Name: fretsonfire
Version: 1.6.1
Summary: Frets on Fire is a game of musical skill and fast fingers.
Author-email: Sami Kyöstilä <skyostil@touko.unrealvoodoo.org>, Roberto Romero <roberto@nirae.at>
License-Expression: GPL-2.0-or-later
Project-URL: Homepage, http://www.unrealvoodoo.org
Keywords: game,music,rhythm,guitar
Classifier: Development Status :: 4 - Beta
Classifier: Intended Audience :: End Users/Desktop
Classifier: Programming Language :: Python
Classifier: Programming Language :: Python :: 3
Classifier: Topic :: Games/Entertainment
Classifier: Topic :: Multimedia :: Sound/Audio
Classifier: Topic :: Multimedia :: Graphics
Requires-Python: >=3.13
License-File: LICENSE.md
Requires-Dist: pygame>=2.1
Requires-Dist: PyOpenGL>=3.1
Requires-Dist: numpy>=1.20
Requires-Dist: Pillow>=9.0
Requires-Dist: pyasyncore>=1.0
Requires-Dist: skia-python>=87.0
Provides-Extra: tests
Requires-Dist: pytest; extra == "tests"
Dynamic: license-file
